Workbook

Sheet 0 客户档案
A1: CRM 分级评分计算器 · 客户档案
A2: 录入客户基础信息（业态会影响阈值调整）
B4: 客户公司名 | C4: 山东 XX 钢管科技
B5: 老板姓名 | C5: 王 X X
B6: 客户业态（钢贸/钢厂/加工/镀锌） | C6: 钢贸
B7: 所在地区（长三角/珠三角/京津冀/华中/西南/其他） | C7: 京津冀
B8: 年流水（万元） | C8: 18000
B9: 员工数 | C9: 50
B10: 成立年份 | C10: 2005
B11: 销售归属 | C11: 李 X X
B12: 评分日期 | C12: 2026-06-15
B13: 数据完整度（%） | C13: 95
A15: 业态阈值调整说明
B16: 钢贸（默认） | C16: 基准阈值
B17: 钢厂 | C17: V1 ×3 / P1 ×1.5 / L1 权重 ↑
B18: 加工 | C18: V1 ×0.5 / V2 权重 ↑ / P1 ×0.7
B19: 镀锌 | C19: V1 ×2 / P1 ×1.2 / 加入锌价对冲信号

Sheet 1 价值维度
A1: 价值维度（V1-V4）（权重 25% 占综合）
A2: 在【实测值】填入您的客户数据，单项分自动计算
A4: 子指标录入
A5: # | B5: 子指标名称 | C5: 数据来源 | D5: 单位 | E5: 实测值 | F5: 等级阈值表 | G5: 单项分
A6: 1 | B6: V1 年采购额 | C6: 订单表：SUM(订单金额) 近12月 | D6: 万元 | E6: 4200 | F6: >= ¥3,000 万 → 100 ¥1,000-3,000 万 → 85 ¥500-1,000 万 → 70 ¥100-500 万 → 50 ¥30-100 万 → 30 < ¥30 万 → 10 | G6: =IF(E6>=3000,100,IF(E6>=3000,100,IF(AND(E6>=1000,E6<3000),85,IF(AND(E6>=500,E6<1000),70,IF(AND(E6>=100,E6<500),50,IF(AND(E6>=30,E6<100),30,10))))))
A7: 2 | B7: V2 月均订单数 | C7: 订单表：COUNT(订单)/12 | D7: 单/月 | E7: 6.5 | F7: >= 8 → 100 4-8 → 80 2-4 → 60 1-2 → 40 < 1 → 20 | G7: =IF(E7>=8,100,IF(E7>=8,100,IF(AND(E7>=4,E7<8),80,IF(AND(E7>=2,E7<4),60,IF(AND(E7>=1,E7<2),40,20)))))
A8: 3 | B8: V3 单笔订单均值 | C8: 订单：SUM/COUNT | D8: 万元 | E8: 54 | F8: >= ¥100 万 → 100 ¥50-100 万 → 85 ¥20-50 万 → 70 ¥5-20 万 → 50 ¥1-5 万 → 30 < ¥1 万 → 10 | G8: =IF(E8>=100,100,IF(E8>=100,100,IF(AND(E8>=50,E8<100),85,IF(AND(E8>=20,E8<50),70,IF(AND(E8>=5,E8<20),50,IF(AND(E8>=1,E8<5),30,10))))))
A9: 4 | B9: V4 SKU 多样度 | C9: 订单明细：COUNT(DISTINCT SKU) | D9: 种 | E9: 18 | F9: >= 30 → 100 15-30 → 80 8-15 → 60 3-8 → 40 < 3 → 20 | G9: =IF(E9>=30,100,IF(E9>=30,100,IF(AND(E9>=15,E9<30),80,IF(AND(E9>=8,E9<15),60,IF(AND(E9>=3,E9<8),40,20)))))
A11: 权重 / 综合分计算
A12: # | B12: 子指标 | C12: 权重（%） | D12: 单项分 | E12: 加权分
A13: 1 | B13: V1 | C13: 40 | D13: =G6 | E13: =C13*D13/100
A14: 2 | B14: V2 | C14: 20 | D14: =G7 | E14: =C14*D14/100
A15: 3 | B15: V3 | C15: 20 | D15: =G8 | E15: =C15*D15/100
A16: 4 | B16: V4 | C16: 20 | D16: =G9 | E16: =C16*D16/100
B17: 维度综合分 | C17: =SUM(C13:C16) | D17: — | E17: =SUM(E13:E16)
A19: 维度公式说明
A20: 维度综合分 = V1×40% + V2×20% + V3×20% + V4×20%（钢厂业态 V1 阈值 ×3 / 加工业态 ×0.5）

Sheet 2 利润维度
A1: 利润维度（P1-P3）（权重 25% 占综合）
A2: 在【实测值】填入您的客户数据，单项分自动计算
A4: 子指标录入
A5: # | B5: 子指标名称 | C5: 数据来源 | D5: 单位 | E5: 实测值 | F5: 等级阈值表 | G5: 单项分
A6: 1 | B6: P1 综合毛利率 | C6: (销售-成本-运费-加工)/销售 | D6: % | E6: 4.5 | F6: >= 6% → 100 4-6% → 85 2-4% → 65 1-2% → 40 0-1% → 15 < 0% → 0 | G6: =IF(E6>=6,100,IF(E6>=6,100,IF(AND(E6>=4,E6<6),85,IF(AND(E6>=2,E6<4),65,IF(AND(E6>=1,E6<2),40,IF(AND(E6>=0,E6<1),15,0))))))
A7: 2 | B7: P2 年贡献毛利占公司比 | C7: 客户毛利/公司总毛利 | D7: % | E7: 1.8 | F7: >= 5% → 100 2-5% → 80 0.5-2% → 60 0.1-0.5% → 40 < 0.1% → 20 | G7: =IF(E7>=5,100,IF(E7>=5,100,IF(AND(E7>=2,E7<5),80,IF(AND(E7>=0.5,E7<2),60,IF(AND(E7>=0.1,E7<0.5),40,20)))))
A8: 3 | B8: P3 利润同比变化 | C8: (今年-去年)/去年 | D8: % | E8: 18 | F8: > +20% → 100 +5% ~ +20% → 80 -5% ~ +5% → 60 -20% ~ -5% → 40 < -20% → 20 | G8: =IF(E8>20,100,IF(E8>20,100,IF(AND(E8>=5,E8<20),80,IF(AND(E8>=-5,E8<5),60,IF(AND(E8>=-20,E8<-5),40,20)))))
A10: 权重 / 综合分计算
A11: # | B11: 子指标 | C11: 权重（%） | D11: 单项分 | E11: 加权分
A12: 1 | B12: P1 | C12: 60 | D12: =G6 | E12: =C12*D12/100
A13: 2 | B13: P2 | C13: 28 | D13: =G7 | E13: =C13*D13/100
A14: 3 | B14: P3 | C14: 12 | D14: =G8 | E14: =C14*D14/100
B15: 维度综合分 | C15: =SUM(C12:C14) | D15: — | E15: =SUM(E12:E14)
A17: 维度公式说明
A18: 维度综合分 = P1×60% + P2×28% + P3×12%（钢厂 P1 阈值 ×1.5 / 加工 ×0.7）★ P1<0% 触发强制不超 C 级

Sheet 3 付款维度
A1: 付款维度（R1-R4）（权重 20% 占综合）
A2: 在【实测值】填入您的客户数据，单项分自动计算
A4: 子指标录入
A5: # | B5: 子指标名称 | C5: 数据来源 | D5: 单位 | E5: 实测值 | F5: 等级阈值表 | G5: 单项分
A6: 1 | B6: R1 应收周转天数 | C6: 平均应收/销售额×365 | D6: 天 | E6: 42 | F6: <= 30 → 100 30-60 → 80 60-90 → 60 90-120 → 35 > 120 → 10 | G6: =IF(E6<=30,100,IF(E6<=30,100,IF(AND(E6>=30,E6<60),80,IF(AND(E6>=60,E6<90),60,IF(AND(E6>=90,E6<120),35,10)))))
A7: 2 | B7: R2 90 天+ 应收占比 | C7: 90天+/总应收 | D7: % | E7: 8 | F7: 0% → 100 0-10% → 85 10-25% → 60 25-50% → 30 > 50% → 5 | G7: =IF(E7<=0,100,IF(E7<=0,100,IF(AND(E7>=0,E7<10),85,IF(AND(E7>=10,E7<25),60,IF(AND(E7>=25,E7<50),30,5)))))
A8: 3 | B8: R3 付款准时率 | C8: 按时付款笔数/总笔数 | D8: % | E8: 92 | F8: >= 95% → 100 85-95% → 80 70-85% → 55 50-70% → 30 < 50% → 10 | G8: =IF(E8>=95,100,IF(E8>=95,100,IF(AND(E8>=85,E8<95),80,IF(AND(E8>=70,E8<85),55,IF(AND(E8>=50,E8<70),30,10)))))
A9: 4 | B9: R4 历史坏账次数 | C9: 坏账登记表 | D9: 次 | E9: 0 | F9: 0 次 → 100 1 次 < ¥10 万（折合 1-1.5） → 70 1 次 ¥10-100 万（折合 1.5-2.5） → 40 1 次 > ¥100 万（折合 2.5-3.5） → 15 >= 2 次（强制黑名单） → 0 | G9: =IF(E9<=0,100,IF(E9<=0,100,IF(AND(E9>=0.5,E9<1.5),70,IF(AND(E9>=1.5,E9<2.5),40,IF(AND(E9>=2.5,E9<3.5),15,0)))))
A11: 权重 / 综合分计算
A12: # | B12: 子指标 | C12: 权重（%） | D12: 单项分 | E12: 加权分
A13: 1 | B13: R1 | C13: 35 | D13: =G6 | E13: =C13*D13/100
A14: 2 | B14: R2 | C14: 30 | D14: =G7 | E14: =C14*D14/100
A15: 3 | B15: R3 | C15: 20 | D15: =G8 | E15: =C15*D15/100
A16: 4 | B16: R4 | C16: 15 | D16: =G9 | E16: =C16*D16/100
B17: 维度综合分 | C17: =SUM(C13:C16) | D17: — | E17: =SUM(E13:E16)
A19: 维度公式说明
A20: 维度综合分 = R1×35% + R2×30% + R3×20% + R4×15%（★ R4>=2 次 / R3<50% / R2>50% 6 月+ 均触发强制 D）

Sheet 4 粘性维度
A1: 粘性维度（L1-L3）（权重 15% 占综合）
A2: 在【实测值】填入您的客户数据，单项分自动计算
A4: 子指标录入
A5: # | B5: 子指标名称 | C5: 数据来源 | D5: 单位 | E5: 实测值 | F5: 等级阈值表 | G5: 单项分
A6: 1 | B6: L1 合作年限 | C6: 首次合作至今 | D6: 年 | E6: 7 | F6: >= 5 → 100 3-5 → 85 1-3 → 65 0.5-1 → 40 < 0.5（新客） → 20 | G6: =IF(E6>=5,100,IF(E6>=5,100,IF(AND(E6>=3,E6<5),85,IF(AND(E6>=1,E6<3),65,IF(AND(E6>=0.5,E6<1),40,20)))))
A7: 2 | B7: L2 近 12 月活跃月数 | C7: 下单月+主动询价月 | D7: 月 | E7: 12 | F7: >= 10 → 100 7-9 → 80 4-6 → 60 1-3 → 30 0（沉睡） → 0 | G7: =IF(E7>=10,100,IF(E7>=10,100,IF(AND(E7>=7,E7<10),80,IF(AND(E7>=4,E7<7),60,IF(AND(E7>=1,E7<4),30,0)))))
A8: 3 | B8: L3 对接深度评分 | C8: 对接人数+EDI+多部门 | D8: 分(0-100) | E8: 80 | F8: >= 80（多部门+EDI） → 100 60-80（2+ 对接人含老板） → 80 40-60（1 对接人 含财务） → 50 20-40（1 对接人 业务） → 30 < 20（绑销售） → 15 | G8: =IF(E8>=80,100,IF(E8>=80,100,IF(AND(E8>=60,E8<80),80,IF(AND(E8>=40,E8<60),50,IF(AND(E8>=20,E8<40),30,15)))))
A10: 权重 / 综合分计算
A11: # | B11: 子指标 | C11: 权重（%） | D11: 单项分 | E11: 加权分
A12: 1 | B12: L1 | C12: 30 | D12: =G6 | E12: =C12*D12/100
A13: 2 | B13: L2 | C13: 40 | D13: =G7 | E13: =C13*D13/100
A14: 3 | B14: L3 | C14: 30 | D14: =G8 | E14: =C14*D14/100
B15: 维度综合分 | C15: =SUM(C12:C14) | D15: — | E15: =SUM(E12:E14)
A17: 维度公式说明
A18: 维度综合分 = L1×30% + L2×40% + L3×30%

Sheet 5 潜力维度
A1: 潜力维度（G1-G4）（权重 15% 占综合）
A2: 在【实测值】填入您的客户数据，单项分自动计算
A4: 子指标录入
A5: # | B5: 子指标名称 | C5: 数据来源 | D5: 单位 | E5: 实测值 | F5: 等级阈值表 | G5: 单项分
A6: 1 | B6: G1 客户行业景气 | C6: 行业研究 + 公开数据 | D6: 分 | E6: 85 | F6: >= 85（出口/新能源/汽车） → 100 65-85（家电/集装箱/五金） → 80 50-65（基建/机械） → 60 30-50（钢结构/工业建筑） → 40 < 30（房地产/普通建筑） → 20 | G6: =IF(E6>=85,100,IF(E6>=85,100,IF(AND(E6>=65,E6<85),80,IF(AND(E6>=50,E6<65),60,IF(AND(E6>=30,E6<50),40,20)))))
A7: 2 | B7: G2 客户自身增长 | C7: 客户营收同比 | D7: % | E7: 22 | F7: > +30% → 100 +10% ~ +30% → 80 -10% ~ +10% → 60 -30% ~ -10% → 35 < -30% → 10 | G7: =IF(E7>30,100,IF(E7>30,100,IF(AND(E7>=10,E7<30),80,IF(AND(E7>=-10,E7<10),60,IF(AND(E7>=-30,E7<-10),35,10)))))
A8: 3 | B8: G3 业态拓展空间 | C8: 客户已买/我能卖 比例 | D8: % | E8: 40 | F8: < 30%（巨大空间） → 100 30-60% → 70 60-80% → 50 80-95% → 30 >= 95%（饱和） → 10 | G8: =IF(E8<30,100,IF(E8<30,100,IF(AND(E8>=30,E8<60),70,IF(AND(E8>=60,E8<80),50,IF(AND(E8>=80,E8<95),30,10)))))
A9: 4 | B9: G4 区域 / 政策红利 | C9: 政策研究 | D9: 分 | E9: 90 | F9: >= 80（长三角/珠三角） → 100 60-80（京津冀雄安） → 70 40-60（华中出口转型） → 55 20-40（西南基建） → 40 < 20 → 25 | G9: =IF(E9>=80,100,IF(E9>=80,100,IF(AND(E9>=60,E9<80),70,IF(AND(E9>=40,E9<60),55,IF(AND(E9>=20,E9<40),40,25)))))
A11: 权重 / 综合分计算
A12: # | B12: 子指标 | C12: 权重（%） | D12: 单项分 | E12: 加权分
A13: 1 | B13: G1 | C13: 30 | D13: =G6 | E13: =C13*D13/100
A14: 2 | B14: G2 | C14: 27 | D14: =G7 | E14: =C14*D14/100
A15: 3 | B15: G3 | C15: 27 | D15: =G8 | E15: =C15*D15/100
A16: 4 | B16: G4 | C16: 16 | D16: =G9 | E16: =C16*D16/100
B17: 维度综合分 | C17: =SUM(C13:C16) | D17: — | E17: =SUM(E13:E16)
A19: 维度公式说明
A20: 维度综合分 = G1×30% + G2×27% + G3×27% + G4×16%

Sheet 6 综合评分
A1: 综合评分 + 等级判定 + 强制规则
A2: 自动汇总 5 维度 + 加权计算 + 强制规则触发
A4: 5 维度综合分
A5: # | B5: 维度 | C5: 权重(%) | D5: 维度分 | E5: 加权分 | F5: 等级判定（独立） | G5: 备注
A6: ① | B6: 价值维度 | C6: 25 | D6: ='1 价值维度'!E17 | E6: =C6*D6/100 | F6: =IF(D6>=85,"S",IF(D6>=70,"A",IF(D6>=55,"B",IF(D6>=40,"C","D")))) | G6: —
A7: ② | B7: 利润维度 | C7: 25 | D7: ='2 利润维度'!E15 | E7: =C7*D7/100 | F7: =IF(D7>=85,"S",IF(D7>=70,"A",IF(D7>=55,"B",IF(D7>=40,"C","D")))) | G7: P1<0% 强制不超 C
A8: ③ | B8: 付款维度 | C8: 20 | D8: ='3 付款维度'!E17 | E8: =C8*D8/100 | F8: =IF(D8>=85,"S",IF(D8>=70,"A",IF(D8>=55,"B",IF(D8>=40,"C","D")))) | G8: R4>=2 强制 D / R3<50% 强制 D
A9: ④ | B9: 粘性维度 | C9: 15 | D9: ='4 粘性维度'!E15 | E9: =C9*D9/100 | F9: =IF(D9>=85,"S",IF(D9>=70,"A",IF(D9>=55,"B",IF(D9>=40,"C","D")))) | G9: —
A10: ⑤ | B10: 潜力维度 | C10: 15 | D10: ='5 潜力维度'!E17 | E10: =C10*D10/100 | F10: =IF(D10>=85,"S",IF(D10>=70,"A",IF(D10>=55,"B",IF(D10>=40,"C","D")))) | G10: —
A12: 综合分（基础）= 5 维度加权和 | E12: =ROUND(SUM(E6:E10),1) | F12: =IF(E12>=85,"S 钻石",IF(E12>=70,"A 黄金",IF(E12>=55,"B 白银",IF(E12>=40,"C 青铜","D 警示")))) | G12: 基础等级
A14: 强制规则（自动检测）
A15: # | B15: 规则 | C15: 触发条件 | D15: — | E15: — | F15: 是否触发 | G15: 效果
A16: ① | B16: R4 >= 2 次坏账 | C16: 付款 R4 实测 >= 4 | F16: =IF(='3 付款维度'!E9>=4,"🔴 触发","✅ 未触发") | G16: 强制 D + 黑名单
A17: ② | B17: R3 准时率 < 50% | C17: 付款 R3 实测 < 50 | F17: =IF(='3 付款维度'!E8<50,"🔴 触发","✅ 未触发") | G17: 强制 D
A18: ③ | B18: R2 90 天+ > 50% | C18: 付款 R2 实测 > 50 | F18: =IF(='3 付款维度'!E7>50,"🔴 触发","✅ 未触发") | G18: 强制 D + 冻结订单
A19: ④ | B19: P1 毛利率 < 0% | C19: 利润 P1 实测 < 0 | F19: =IF(='2 利润维度'!E6<0,"🔴 触发","✅ 未触发") | G19: 强制不超 C 级
A21: 最终等级（基础 + 强制规则覆盖）
A22: 客户最终等级 | E22: =IF(='3 付款维度'!E9>=4,"D 钻石 → 强制 D + 黑名单",IF(='3 付款维度'!E8<50,"D → 强制 D",IF(='3 付款维度'!E7>50,"D → 强制 D + 冻结订单",IF(AND(='2 利润维度'!E6<0,OR(F12="S 钻石",F12="A 黄金",F12="B 白银")),"C 青铜 → P1<0 不超 C",F12))))
A24: 特殊标签（独立于等级）
B25: 🔴 风险预警 | C25: =IF(OR('3 付款维度'!E6>90,'3 付款维度'!E7>30),"是","否")
B26: 🟡 沉睡客户 | C26: =IF('4 粘性维度'!E7<=0,"是","否")
B27: 🟢 战略客户 | C27: （老板手动标记）
B28: ⚫ 黑名单 | C28: =IF('3 付款维度'!E9>=4,"是","否")

Sheet 7 五级 SOP
A1: 客户等级 → 销售 SOP（自动匹配）
A2: 当前客户等级：从'6 综合评分'读取（'6 综合评分'!E22）
B4: 当前客户等级： | D4: ='6 综合评分'!E22
A6: 5 级 SOP 总表（销售必读）
A7: 等级 | B7: 主跟人 | C7: 维护频率 | D7: 资源配额(年/客户) | E7: 总数控制 | F7: 续单率KPI
A8: S 钻石 ≥85 | B8: 销售老板/总监 | C8: 月度上门+周电话+日微信 | D8: ¥5-10 万 | E8: ≤ 5%（75 个） | F8: ≥ 95%
A9: A 黄金 70-84 | B9: 销售总监/资深 | C9: 双周上门+周电话 | D9: ¥1-3 万 | E9: 15-20%（250 个） | F9: ≥ 90%
A10: B 白银 55-69 | B10: 销售员 | C10: 月度电话+季上门 | D10: ¥3,000-1 万 | E10: 40-50%（700 个） | F10: ≥ 75%
A11: C 青铜 40-54 | B11: 自动化为主 | C11: 季度 SMS+半年电话 | D11: ≤ ¥1,000 | E11: 25-30%（400 个） | F11: 升 B≥15%/年
A12: D 警示 <40 | B12: 法务/风控/应收 | C12: 催收/黑名单评估 | D12: — | E12: ≤ 10%（150 个） | F12: 坏账≤1%
A14: ★ 当前客户的详细 SOP（自动匹配）
A15: =IF(ISNUMBER(SEARCH("S",D4)),"S 钻石：① 老板亲自月度电话 ② 销售总监双周上门 ③ 月度对账+应收清账+下月预订单 ④ 季度邀请进老板局 ⑤ 半年二代俱乐部 ⑥ 年度战略对话+送年货",IF(ISNUMBER(SEARCH("A",D4)),"A 黄金：① 销售总监双周上门 ② 月度对账+应收 ③ 季度业务回顾 ④ 老板局年度 1-2 次 ⑤ 升 S 提名（连续 2 季 ≥85 分）",IF(ISNUMBER(SEARCH("B",D4)),"B 白银：① 销售员月度电话 ② 季度上门 1 次 ③ 半年健康度自评邀请 ④ 升级路径明确化 ⑤ 跨季评估升 A",IF(ISNUMBER(SEARCH("C",D4)),"C 青铜：① 自动化群发月度行情 ② 季度群发新品/优惠 ③ 半年电话调研 ④ 升 B / 降 D 评估 ⑤ 自动化覆盖 ≥ 90%","D 警示：① 法务催收（30/60/90 天三级） ② 持续不付款=法律诉讼 ③ 进黑名单 ④ 客户主动表态触发反向挽回 SOP ⑤ 6 月观察期重新评估"))))
A23: 提成挂钩规则
A24: 等级 | B24: 提成系数 | C24: — | D24: — | E24: — | F24: —
A25: S | B25: ×1.5
A26: A | B26: ×1.2
A27: B | B27: ×1.0
A28: C | B28: ×0.6
A29: D | B29: ×0 + 倒罚

Sheet 8 批量录入
A1: 50 客户批量录入与评级（每行 1 个客户）
A2: 黄色列录入实测值 / 绿色列自动计算 / 末列自动等级
A4: # | B4: 客户名 | C4: 业态 | D4: V1 | E4: V2 | F4: V3 | G4: V4 | H4: P1 | I4: P2 | J4: P3 | K4: R1 | L4: R2 | M4: R3 | N4: R4 | O4: L1 | P4: L2 | Q4: L3 | R4: G1 | S4: G2 | T4: G3 | U4: G4 | V4: 价值分 | W4: 利润分 | X4: 付款分 | Y4: 粘性分 | Z4: 潜力分 | AA4: 综合分 | AB4: 等级
A5: 1 | B5: 山东 XX 钢管 | C5: 钢贸 | D5: 4200 | E5: 6.5 | F5: 54 | G5: 18 | H5: 4.5 | I5: 1.8 | J5: 18 | K5: 42 | L5: 8 | M5: 92 | N5: 0 | O5: 7 | P5: 12 | Q5: 80 | R5: 85 | S5: 22 | T5: 40 | U5: 90 | V5: =ROUND((IF(D5>=3000,100,IF(D5>=1000,85,IF(D5>=500,70,IF(D5>=100,50,IF(D5>=30,30,10))))))*0.4+(IF(E5>=8,100,IF(E5>=4,80,IF(E5>=2,60,IF(E5>=1,40,20)))))*0.2+(IF(F5>=100,100,IF(F5>=50,85,IF(F5>=20,70,IF(F5>=5,50,IF(F5>=1,30,10))))))*0.2+(IF(G5>=30,100,IF(G5>=15,80,IF(G5>=8,60,IF(G5>=3,40,20)))))*0.2,1) | W5: =ROUND((IF(H5>=6,100,IF(H5>=4,85,IF(H5>=2,65,IF(H5>=1,40,IF(H5>=0,15,0))))))*0.6+(IF(I5>=5,100,IF(I5>=2,80,IF(I5>=0.5,60,IF(I5>=0.1,40,20)))))*0.28+(IF(J5>20,100,IF(J5>=5,80,IF(J5>=-5,60,IF(J5>=-20,40,20)))))*0.12,1) | X5: =ROUND((IF(K5<=30,100,IF(K5<=60,80,IF(K5<=90,60,IF(K5<=120,35,10)))))*0.35+(IF(L5<=0,100,IF(L5<=10,85,IF(L5<=25,60,IF(L5<=50,30,5)))))*0.3+(IF(M5>=95,100,IF(M5>=85,80,IF(M5>=70,55,IF(M5>=50,30,10)))))*0.2+(IF(N5<=0,100,IF(N5<=1,70,IF(N5<=2,40,IF(N5<=3,15,0)))))*0.15,1) | Y5: =ROUND((IF(O5>=5,100,IF(O5>=3,85,IF(O5>=1,65,IF(O5>=0.5,40,20)))))*0.3+(IF(P5>=10,100,IF(P5>=7,80,IF(P5>=4,60,IF(P5>=1,30,0)))))*0.4+(IF(Q5>=80,100,IF(Q5>=60,80,IF(Q5>=40,50,IF(Q5>=20,30,15)))))*0.3,1) | Z5: =ROUND((IF(R5>=85,100,IF(R5>=65,80,IF(R5>=50,60,IF(R5>=30,40,20)))))*0.3+(IF(S5>30,100,IF(S5>=10,80,IF(S5>=-10,60,IF(S5>=-30,35,10)))))*0.27+(IF(T5<30,100,IF(T5<60,70,IF(T5<80,50,IF(T5<95,30,10)))))*0.27+(IF(U5>=80,100,IF(U5>=60,70,IF(U5>=40,55,IF(U5>=20,40,25)))))*0.16,1) | AA5: =ROUND(V5*0.25+W5*0.25+X5*0.2+Y5*0.15+Z5*0.15,1) | AB5: =IF(N5>=2,"D 黑名单",IF(M5<50,"D 强制",IF(L5>50,"D 冻结",IF(H5<0,IF(AA5>=55,"C P1<0",IF(AA5>=40,"C",IF(AA5>=30,"C","D"))),IF(AA5>=85,"S 钻石",IF(AA5>=70,"A 黄金",IF(AA5>=55,"B 白银",IF(AA5>=40,"C 青铜","D 警示"))))))))
A6: 2 | B6: 江苏 XX 焊管 | C6: 钢贸 | D6: 1200 | E6: 4 | F6: 30 | G6: 12 | H6: 3.8 | I6: 0.6 | J6: 8 | K6: 55 | L6: 18 | M6: 78 | N6: 0 | O6: 5 | P6: 10 | Q6: 60 | R6: 75 | S6: 18 | T6: 50 | U6: 80 | V6: =ROUND((IF(D6>=3000,100,IF(D6>=1000,85,IF(D6>=500,70,IF(D6>=100,50,IF(D6>=30,30,10))))))*0.4+(IF(E6>=8,100,IF(E6>=4,80,IF(E6>=2,60,IF(E6>=1,40,20)))))*0.2+(IF(F6>=100,100,IF(F6>=50,85,IF(F6>=20,70,IF(F6>=5,50,IF(F6>=1,30,10))))))*0.2+(IF(G6>=30,100,IF(G6>=15,80,IF(G6>=8,60,IF(G6>=3,40,20)))))*0.2,1) | W6: =ROUND((IF(H6>=6,100,IF(H6>=4,85,IF(H6>=2,65,IF(H6>=1,40,IF(H6>=0,15,0))))))*0.6+(IF(I6>=5,100,IF(I6>=2,80,IF(I6>=0.5,60,IF(I6>=0.1,40,20)))))*0.28+(IF(J6>20,100,IF(J6>=5,80,IF(J6>=-5,60,IF(J6>=-20,40,20)))))*0.12,1) | X6: =ROUND((IF(K6<=30,100,IF(K6<=60,80,IF(K6<=90,60,IF(K6<=120,35,10)))))*0.35+(IF(L6<=0,100,IF(L6<=10,85,IF(L6<=25,60,IF(L6<=50,30,5)))))*0.3+(IF(M6>=95,100,IF(M6>=85,80,IF(M6>=70,55,IF(M6>=50,30,10)))))*0.2+(IF(N6<=0,100,IF(N6<=1,70,IF(N6<=2,40,IF(N6<=3,15,0)))))*0.15,1) | Y6: =ROUND((IF(O6>=5,100,IF(O6>=3,85,IF(O6>=1,65,IF(O6>=0.5,40,20)))))*0.3+(IF(P6>=10,100,IF(P6>=7,80,IF(P6>=4,60,IF(P6>=1,30,0)))))*0.4+(IF(Q6>=80,100,IF(Q6>=60,80,IF(Q6>=40,50,IF(Q6>=20,30,15)))))*0.3,1) | Z6: =ROUND((IF(R6>=85,100,IF(R6>=65,80,IF(R6>=50,60,IF(R6>=30,40,20)))))*0.3+(IF(S6>30,100,IF(S6>=10,80,IF(S6>=-10,60,IF(S6>=-30,35,10)))))*0.27+(IF(T6<30,100,IF(T6<60,70,IF(T6<80,50,IF(T6<95,30,10)))))*0.27+(IF(U6>=80,100,IF(U6>=60,70,IF(U6>=40,55,IF(U6>=20,40,25)))))*0.16,1) | AA6: =ROUND(V6*0.25+W6*0.25+X6*0.2+Y6*0.15+Z6*0.15,1) | AB6: =IF(N6>=2,"D 黑名单",IF(M6<50,"D 强制",IF(L6>50,"D 冻结",IF(H6<0,IF(AA6>=55,"C P1<0",IF(AA6>=40,"C",IF(AA6>=30,"C","D"))),IF(AA6>=85,"S 钻石",IF(AA6>=70,"A 黄金",IF(AA6>=55,"B 白银",IF(AA6>=40,"C 青铜","D 警示"))))))))
A7: 3 | B7: 浙江 XX 冷卷 | C7: 镀锌 | D7: 6000 | E7: 8 | F7: 75 | G7: 20 | H7: 4.2 | I7: 2 | J7: 20 | K7: 38 | L7: 5 | M7: 95 | N7: 0 | O7: 8 | P7: 12 | Q7: 90 | R7: 92 | S7: 25 | T7: 35 | U7: 85 | V7: =ROUND((IF(D7>=3000,100,IF(D7>=1000,85,IF(D7>=500,70,IF(D7>=100,50,IF(D7>=30,30,10))))))*0.4+(IF(E7>=8,100,IF(E7>=4,80,IF(E7>=2,60,IF(E7>=1,40,20)))))*0.2+(IF(F7>=100,100,IF(F7>=50,85,IF(F7>=20,70,IF(F7>=5,50,IF(F7>=1,30,10))))))*0.2+(IF(G7>=30,100,IF(G7>=15,80,IF(G7>=8,60,IF(G7>=3,40,20)))))*0.2,1) | W7: =ROUND((IF(H7>=6,100,IF(H7>=4,85,IF(H7>=2,65,IF(H7>=1,40,IF(H7>=0,15,0))))))*0.6+(IF(I7>=5,100,IF(I7>=2,80,IF(I7>=0.5,60,IF(I7>=0.1,40,20)))))*0.28+(IF(J7>20,100,IF(J7>=5,80,IF(J7>=-5,60,IF(J7>=-20,40,20)))))*0.12,1) | X7: =ROUND((IF(K7<=30,100,IF(K7<=60,80,IF(K7<=90,60,IF(K7<=120,35,10)))))*0.35+(IF(L7<=0,100,IF(L7<=10,85,IF(L7<=25,60,IF(L7<=50,30,5)))))*0.3+(IF(M7>=95,100,IF(M7>=85,80,IF(M7>=70,55,IF(M7>=50,30,10)))))*0.2+(IF(N7<=0,100,IF(N7<=1,70,IF(N7<=2,40,IF(N7<=3,15,0)))))*0.15,1) | Y7: =ROUND((IF(O7>=5,100,IF(O7>=3,85,IF(O7>=1,65,IF(O7>=0.5,40,20)))))*0.3+(IF(P7>=10,100,IF(P7>=7,80,IF(P7>=4,60,IF(P7>=1,30,0)))))*0.4+(IF(Q7>=80,100,IF(Q7>=60,80,IF(Q7>=40,50,IF(Q7>=20,30,15)))))*0.3,1) | Z7: =ROUND((IF(R7>=85,100,IF(R7>=65,80,IF(R7>=50,60,IF(R7>=30,40,20)))))*0.3+(IF(S7>30,100,IF(S7>=10,80,IF(S7>=-10,60,IF(S7>=-30,35,10)))))*0.27+(IF(T7<30,100,IF(T7<60,70,IF(T7<80,50,IF(T7<95,30,10)))))*0.27+(IF(U7>=80,100,IF(U7>=60,70,IF(U7>=40,55,IF(U7>=20,40,25)))))*0.16,1) | AA7: =ROUND(V7*0.25+W7*0.25+X7*0.2+Y7*0.15+Z7*0.15,1) | AB7: =IF(N7>=2,"D 黑名单",IF(M7<50,"D 强制",IF(L7>50,"D 冻结",IF(H7<0,IF(AA7>=55,"C P1<0",IF(AA7>=40,"C",IF(AA7>=30,"C","D"))),IF(AA7>=85,"S 钻石",IF(AA7>=70,"A 黄金",IF(AA7>=55,"B 白银",IF(AA7>=40,"C 青铜","D 警示"))))))))
A8: 4 | B8: 广东 XX 钢贸 | C8: 钢贸 | D8: 3000 | E8: 7 | F8: 43 | G8: 15 | H8: 3.2 | I8: 1.5 | J8: 10 | K8: 48 | L8: 12 | M8: 85 | N8: 0 | O8: 6 | P8: 11 | Q8: 70 | R8: 70 | S8: 20 | T8: 45 | U8: 75 | V8: =ROUND((IF(D8>=3000,100,IF(D8>=1000,85,IF(D8>=500,70,IF(D8>=100,50,IF(D8>=30,30,10))))))*0.4+(IF(E8>=8,100,IF(E8>=4,80,IF(E8>=2,60,IF(E8>=1,40,20)))))*0.2+(IF(F8>=100,100,IF(F8>=50,85,IF(F8>=20,70,IF(F8>=5,50,IF(F8>=1,30,10))))))*0.2+(IF(G8>=30,100,IF(G8>=15,80,IF(G8>=8,60,IF(G8>=3,40,20)))))*0.2,1) | W8: =ROUND((IF(H8>=6,100,IF(H8>=4,85,IF(H8>=2,65,IF(H8>=1,40,IF(H8>=0,15,0))))))*0.6+(IF(I8>=5,100,IF(I8>=2,80,IF(I8>=0.5,60,IF(I8>=0.1,40,20)))))*0.28+(IF(J8>20,100,IF(J8>=5,80,IF(J8>=-5,60,IF(J8>=-20,40,20)))))*0.12,1) | X8: =ROUND((IF(K8<=30,100,IF(K8<=60,80,IF(K8<=90,60,IF(K8<=120,35,10)))))*0.35+(IF(L8<=0,100,IF(L8<=10,85,IF(L8<=25,60,IF(L8<=50,30,5)))))*0.3+(IF(M8>=95,100,IF(M8>=85,80,IF(M8>=70,55,IF(M8>=50,30,10)))))*0.2+(IF(N8<=0,100,IF(N8<=1,70,IF(N8<=2,40,IF(N8<=3,15,0)))))*0.15,1) | Y8: =ROUND((IF(O8>=5,100,IF(O8>=3,85,IF(O8>=1,65,IF(O8>=0.5,40,20)))))*0.3+(IF(P8>=10,100,IF(P8>=7,80,IF(P8>=4,60,IF(P8>=1,30,0)))))*0.4+(IF(Q8>=80,100,IF(Q8>=60,80,IF(Q8>=40,50,IF(Q8>=20,30,15)))))*0.3,1) | Z8: =ROUND((IF(R8>=85,100,IF(R8>=65,80,IF(R8>=50,60,IF(R8>=30,40,20)))))*0.3+(IF(S8>30,100,IF(S8>=10,80,IF(S8>=-10,60,IF(S8>=-30,35,10)))))*0.27+(IF(T8<30,100,IF(T8<60,70,IF(T8<80,50,IF(T8<95,30,10)))))*0.27+(IF(U8>=80,100,IF(U8>=60,70,IF(U8>=40,55,IF(U8>=20,40,25)))))*0.16,1) | AA8: =ROUND(V8*0.25+W8*0.25+X8*0.2+Y8*0.15+Z8*0.15,1) | AB8: =IF(N8>=2,"D 黑名单",IF(M8<50,"D 强制",IF(L8>50,"D 冻结",IF(H8<0,IF(AA8>=55,"C P1<0",IF(AA8>=40,"C",IF(AA8>=30,"C","D"))),IF(AA8>=85,"S 钻石",IF(AA8>=70,"A 黄金",IF(AA8>=55,"B 白银",IF(AA8>=40,"C 青铜","D 警示"))))))))
A9: 5 | B9: 邯郸 XX 钢管 | C9: 钢贸 | D9: 3000 | E9: 5.5 | F9: 55 | G9: 18 | H9: 4 | I9: 1.2 | J9: -5 | K9: 65 | L9: 25 | M9: 75 | N9: 1 | O9: 6 | P9: 12 | Q9: 75 | R9: 60 | S9: -10 | T9: 30 | U9: 60 | V9: =ROUND((IF(D9>=3000,100,IF(D9>=1000,85,IF(D9>=500,70,IF(D9>=100,50,IF(D9>=30,30,10))))))*0.4+(IF(E9>=8,100,IF(E9>=4,80,IF(E9>=2,60,IF(E9>=1,40,20)))))*0.2+(IF(F9>=100,100,IF(F9>=50,85,IF(F9>=20,70,IF(F9>=5,50,IF(F9>=1,30,10))))))*0.2+(IF(G9>=30,100,IF(G9>=15,80,IF(G9>=8,60,IF(G9>=3,40,20)))))*0.2,1) | W9: =ROUND((IF(H9>=6,100,IF(H9>=4,85,IF(H9>=2,65,IF(H9>=1,40,IF(H9>=0,15,0))))))*0.6+(IF(I9>=5,100,IF(I9>=2,80,IF(I9>=0.5,60,IF(I9>=0.1,40,20)))))*0.28+(IF(J9>20,100,IF(J9>=5,80,IF(J9>=-5,60,IF(J9>=-20,40,20)))))*0.12,1) | X9: =ROUND((IF(K9<=30,100,IF(K9<=60,80,IF(K9<=90,60,IF(K9<=120,35,10)))))*0.35+(IF(L9<=0,100,IF(L9<=10,85,IF(L9<=25,60,IF(L9<=50,30,5)))))*0.3+(IF(M9>=95,100,IF(M9>=85,80,IF(M9>=70,55,IF(M9>=50,30,10)))))*0.2+(IF(N9<=0,100,IF(N9<=1,70,IF(N9<=2,40,IF(N9<=3,15,0)))))*0.15,1) | Y9: =ROUND((IF(O9>=5,100,IF(O9>=3,85,IF(O9>=1,65,IF(O9>=0.5,40,20)))))*0.3+(IF(P9>=10,100,IF(P9>=7,80,IF(P9>=4,60,IF(P9>=1,30,0)))))*0.4+(IF(Q9>=80,100,IF(Q9>=60,80,IF(Q9>=40,50,IF(Q9>=20,30,15)))))*0.3,1) | Z9: =ROUND((IF(R9>=85,100,IF(R9>=65,80,IF(R9>=50,60,IF(R9>=30,40,20)))))*0.3+(IF(S9>30,100,IF(S9>=10,80,IF(S9>=-10,60,IF(S9>=-30,35,10)))))*0.27+(IF(T9<30,100,IF(T9<60,70,IF(T9<80,50,IF(T9<95,30,10)))))*0.27+(IF(U9>=80,100,IF(U9>=60,70,IF(U9>=40,55,IF(U9>=20,40,25)))))*0.16,1) | AA9: =ROUND(V9*0.25+W9*0.25+X9*0.2+Y9*0.15+Z9*0.15,1) | AB9: =IF(N9>=2,"D 黑名单",IF(M9<50,"D 强制",IF(L9>50,"D 冻结",IF(H9<0,IF(AA9>=55,"C P1<0",IF(AA9>=40,"C",IF(AA9>=30,"C","D"))),IF(AA9>=85,"S 钻石",IF(AA9>=70,"A 黄金",IF(AA9>=55,"B 白银",IF(AA9>=40,"C 青铜","D 警示"))))))))
A10: 6 | B10: 天津 XX 钢贸 | C10: 钢贸 | D10: 800 | E10: 3.5 | F10: 23 | G10: 10 | H10: 2 | I10: 0.3 | J10: -15 | K10: 95 | L10: 38 | M10: 60 | N10: 2 | O10: 4 | P10: 8 | Q10: 50 | R10: 45 | S10: -20 | T10: 55 | U10: 60 | V10: =ROUND((IF(D10>=3000,100,IF(D10>=1000,85,IF(D10>=500,70,IF(D10>=100,50,IF(D10>=30,30,10))))))*0.4+(IF(E10>=8,100,IF(E10>=4,80,IF(E10>=2,60,IF(E10>=1,40,20)))))*0.2+(IF(F10>=100,100,IF(F10>=50,85,IF(F10>=20,70,IF(F10>=5,50,IF(F10>=1,30,10))))))*0.2+(IF(G10>=30,100,IF(G10>=15,80,IF(G10>=8,60,IF(G10>=3,40,20)))))*0.2,1) | W10: =ROUND((IF(H10>=6,100,IF(H10>=4,85,IF(H10>=2,65,IF(H10>=1,40,IF(H10>=0,15,0))))))*0.6+(IF(I10>=5,100,IF(I10>=2,80,IF(I10>=0.5,60,IF(I10>=0.1,40,20)))))*0.28+(IF(J10>20,100,IF(J10>=5,80,IF(J10>=-5,60,IF(J10>=-20,40,20)))))*0.12,1) | X10: =ROUND((IF(K10<=30,100,IF(K10<=60,80,IF(K10<=90,60,IF(K10<=120,35,10)))))*0.35+(IF(L10<=0,100,IF(L10<=10,85,IF(L10<=25,60,IF(L10<=50,30,5)))))*0.3+(IF(M10>=95,100,IF(M10>=85,80,IF(M10>=70,55,IF(M10>=50,30,10)))))*0.2+(IF(N10<=0,100,IF(N10<=1,70,IF(N10<=2,40,IF(N10<=3,15,0)))))*0.15,1) | Y10: =ROUND((IF(O10>=5,100,IF(O10>=3,85,IF(O10>=1,65,IF(O10>=0.5,40,20)))))*0.3+(IF(P10>=10,100,IF(P10>=7,80,IF(P10>=4,60,IF(P10>=1,30,0)))))*0.4+(IF(Q10>=80,100,IF(Q10>=60,80,IF(Q10>=40,50,IF(Q10>=20,30,15)))))*0.3,1) | Z10: =ROUND((IF(R10>=85,100,IF(R10>=65,80,IF(R10>=50,60,IF(R10>=30,40,20)))))*0.3+(IF(S10>30,100,IF(S10>=10,80,IF(S10>=-10,60,IF(S10>=-30,35,10)))))*0.27+(IF(T10<30,100,IF(T10<60,70,IF(T10<80,50,IF(T10<95,30,10)))))*0.27+(IF(U10>=80,100,IF(U10>=60,70,IF(U10>=40,55,IF(U10>=20,40,25)))))*0.16,1) | AA10: =ROUND(V10*0.25+W10*0.25+X10*0.2+Y10*0.15+Z10*0.15,1) | AB10: =IF(N10>=2,"D 黑名单",IF(M10<50,"D 强制",IF(L10>50,"D 冻结",IF(H10<0,IF(AA10>=55,"C P1<0",IF(AA10>=40,"C",IF(AA10>=30,"C","D"))),IF(AA10>=85,"S 钻石",IF(AA10>=70,"A 黄金",IF(AA10>=55,"B 白银",IF(AA10>=40,"C 青铜","D 警示"))))))))
A11: 7
A12: 8
A13: 9
A14: 10
A15: 11
A16: 12
A17: 13
A18: 14
A19: 15
A20: 16
A21: 17
A22: 18
... A54: 50
A56: 使用说明
A57: 1. 黄色单元格 = 录入区（V1-V4 / P1-P3 / R1-R4 / L1-L3 / G1-G4 共 18 个子指标）
A58: 2. 绿色单元格 = 自动计算（5 维度分 + 综合分）
A59: 3. 金色单元格 = 综合分
A60: 4. 深绿色单元格 = 最终等级（含强制规则）
A61: 5. 强制规则：R4≥2=D黑名单 / R3<50=D强制 / R2>50=D冻结 / P1<0=不超 C
A62: 6. 可拖拽公式至 50 行批量评级

Sheet 9 维度说明
A1: 5 维度 × 18 子指标速查
A2: 完整规则见 docs/69-CRM分级落地细则与评估细节.md
A4: # | B4: 维度 | C4: 权重 | D4: 子指标 | E4: 权重 | F4: 说明
A5: ① | B5: 价值 | C5: 25% | D5: V1 年采购额 | E5: 40% | F5: 近 12 月订单总额（钢厂×3 / 加工×0.5）
D6: V2 月均订单数 | E6: 20% | F6: 近 12 月订单数 / 12
D7: V3 单笔均值 | E7: 20% | F7: 订单总额 / 订单数
D8: V4 SKU 多样度 | E8: 20% | F8: 近 12 月不重复 SKU 数
A9: ② | B9: 利润 | C9: 25% | D9: P1 综合毛利率 | E9: 60% | F9: ★ <0% 强制不超 C
D10: P2 年贡献毛利占公司 | E10: 28% | F10: 客户毛利 / 公司总毛利
D11: P3 利润同比 | E11: 12% | F11: 今年毛利 vs 去年
A12: ③ | B12: 付款 | C12: 20% | D12: R1 应收周转天数 | E12: 35% | F12: 平均应收/销售×365
D13: R2 90 天+ 应收占比 | E13: 30% | F13: ★ >50% 强制 D + 冻结
D14: R3 付款准时率 | E14: 20% | F14: ★ <50% 强制 D
D15: R4 历史坏账次数 | E15: 15% | F15: ★ ≥2 次强制 D + 黑名单
A16: ④ | B16: 粘性 | C16: 15% | D16: L1 合作年限 | E16: 30% | F16: 首次合作至今
D17: L2 近 12 月活跃度 | E17: 40% | F17: 下单/询价月数
D18: L3 对接深度 | E18: 30% | F18: 对接人数 + EDI + 多部门
A19: ⑤ | B19: 潜力 | C19: 15% | D19: G1 客户行业景气 | E19: 30% | F19: 汽车/家电/出口 高
D20: G2 客户自身增长 | E20: 27% | F20: 客户营收同比
D21: G3 业态拓展空间 | E21: 27% | F21: 客户已买/我能卖 比例
D22: G4 区域/政策红利 | E22: 16% | F22: 长三角/雄安/出口
A25: 5 级评分边界 + 强制规则
A26: 等级 | B26: 分数区间 | C26: — | D26: 占比目标 | E26: — | F26: 强制触发
A27: S 钻石 | B27: ≥ 85 | D27: ≤ 5% | F27: —
A28: A 黄金 | B28: 70-84 | D28: 15-20% | F28: —
A29: B 白银 | B29: 55-69 | D29: 40-50% | F29: —
A30: C 青铜 | B30: 40-54 | D30: 25-30% | F30: P1<0% 不超 C
A31: D 警示 | B31: < 40 | D31: ≤ 10% | F31: R4≥2 / R3<50% / R2>50%
