Workbook

Sheet 使用说明
B2: 3 业务跨业务财务整合模型
B4: 3 业务 | C4: 业务 1 钢厂主业 / 业务 2 钢贸 SaaS / 业务 3 平台+信用数据
B5: 使用步骤 | C5: ① 业务 1/2/3 各自 sheet → 调整黄色单元格 ② 切换『3 业务合并损益』看年度汇总 ③ 切换『3 业务合并现金流』看 36 月月度 ④ 切换『协同效应测算』看跨业务价值 ⑤ 切换『估值与融资』看每年融资节奏
B6: 基准假设 | C6: - 业务 1 钢厂 Y1 ¥800 万 / Y2 ¥2500 万 / Y3 ¥5500 万 - 业务 2 钢贸 SaaS Y1 ¥150 万 / Y2 ¥1900 万 / Y3 ¥2.5 亿 - 业务 3 平台+数据 Y1 ¥50 万 / Y2 ¥700 万 / Y3 ¥5300 万 - 3 业务 3 年合计 ¥3.7 亿
B7: 关键产出 | C7: 1. 3 业务整合 ARR 2. 跨业务协同价值（CAC 降低 / LTV 提升） 3. 每年融资缺口 / 自我造血能力 4. 估值演进 + 融资轮次时点

Sheet 业务1钢厂主业
B2: 业务 1：钢厂数字化 SaaS（3 年）
B4: 项 | C4: Y1 | D4: Y2 | E4: Y3 | F4: 3 年累计
B5: ▼ 收入
B6: 实施费收入 | C6: 4000000 | D6: 10000000 | E6: 22000000 | F6: =SUM(C6:E6)
B7: 月租 SaaS 收入 | C7: 3500000 | D7: 13500000 | E7: 30000000 | F7: =SUM(C7:E7)
B8: 增值服务 | C8: 500000 | D8: 1500000 | E8: 3000000 | F8: =SUM(C8:E8)
B9: 总收入 | C9: =SUM(C6:C8) | D9: =SUM(D6:D8) | E9: =SUM(E6:E8) | F9: =SUM(F6:F8)
B11: ▼ 成本
B12: 人力成本（销售+实施+客服） | C12: 2400000 | D12: 5500000 | E12: 11000000 | F12: =SUM(C12:E12)
B13: 营销 + 老板局 + 物料 | C13: 1000000 | D13: 2000000 | E13: 4000000 | F13: =SUM(C13:E13)
B14: 产品 + 技术 + 数据 | C14: 800000 | D14: 1500000 | E14: 2500000 | F14: =SUM(C14:E14)
B15: 行政 + 财务 + 其他 | C15: 400000 | D15: 600000 | E15: 1000000 | F15: =SUM(C15:E15)
B16: 总成本 | C16: =SUM(C12:C15) | D16: =SUM(D12:D15) | E16: =SUM(E12:E15) | F16: =SUM(F12:F15)
B18: 净利润 | C18: =C9-C16 | D18: =D9-D16 | E18: =E9-E16 | F18: =F9-F16

Sheet 业务2钢贸SaaS
B2: 业务 2：钢贸企业 SaaS（3 年）
B4: 项 | C4: Y1 | D4: Y2 | E4: Y3 | F4: 3 年累计
B5: ▼ 收入
B6: ERP/WMS 实施费 | C6: 500000 | D6: 6000000 | E6: 30000000 | F6: =SUM(C6:E6)
B7: AI 月费订阅 | C7: 1000000 | D7: 13000000 | E7: 200000000 | F7: =SUM(C7:E7)
B8: 货袋子+现货平台增值 | C8: 0 | D8: 500000 | E8: 5000000 | F8: =SUM(C8:E8)
B9: 咨询服务（接班+战略） | C9: 0 | D9: 1000000 | E9: 10000000 | F9: =SUM(C9:E9)
B10: 总收入 | C10: =SUM(C6:C9) | D10: =SUM(D6:D9) | E10: =SUM(E6:E9) | F10: =SUM(F6:F9)
B12: ▼ 成本
B13: 人力（销售+CS+顾问） | C13: 1000000 | D13: 6000000 | E13: 30000000 | F13: =SUM(C13:E13)
B14: 营销 + 推广 | C14: 200000 | D14: 1500000 | E14: 8000000 | F14: =SUM(C14:E14)
B15: 产品 + AI + 数据 | C15: 800000 | D15: 3000000 | E15: 15000000 | F15: =SUM(C15:E15)
B16: 自营 GMV + 平台运营 | C16: 100000 | D16: 2000000 | E16: 10000000 | F16: =SUM(C16:E16)
B17: 行政 + 其他 | C17: 100000 | D17: 500000 | E17: 3000000 | F17: =SUM(C17:E17)
B18: 总成本 | C18: =SUM(C13:C17) | D18: =SUM(D13:D17) | E18: =SUM(E13:E17) | F18: =SUM(F13:F17)
B20: 净利润 | C20: =C10-C18 | D20: =D10-D18 | E20: =E10-E18 | F20: =F10-F18

Sheet 业务3平台数据
B2: 业务 3：交易平台 + 信用数据（3 年）
B4: 项 | C4: Y1 | D4: Y2 | E4: Y3 | F4: 3 年累计
B5: ▼ 收入
B6: 撮合佣金 | C6: 300000 | D6: 4000000 | E6: 25000000 | F6: =SUM(C6:E6)
B7: 仓储+物流分润 | C7: 200000 | D7: 1800000 | E7: 14000000 | F7: =SUM(C7:E7)
B8: 信用数据外卖 | C8: 0 | D8: 1000000 | E8: 13000000 | F8: =SUM(C8:E8)
B9: 票据+担保服务费 | C9: 0 | D9: 200000 | E9: 1000000 | F9: =SUM(C9:E9)
B10: 总收入 | C10: =SUM(C6:C9) | D10: =SUM(D6:D9) | E10: =SUM(E6:E9) | F10: =SUM(F6:F9)
B12: ▼ 成本
B13: 人力（BD+数据销售+运营） | C13: 300000 | D13: 2000000 | E13: 10000000 | F13: =SUM(C13:E13)
B14: 营销 + 行业 KOL | C14: 100000 | D14: 600000 | E14: 3000000 | F14: =SUM(C14:E14)
B15: 数据 + 算法 + 风控 | C15: 200000 | D15: 1000000 | E15: 5000000 | F15: =SUM(C15:E15)
B16: 行政 + 其他 | C16: 50000 | D16: 200000 | E16: 1000000 | F16: =SUM(C16:E16)
B17: 总成本 | C17: =SUM(C13:C16) | D17: =SUM(D13:D16) | E17: =SUM(E13:E16) | F17: =SUM(F13:F16)
B19: 净利润 | C19: =C10-C17 | D19: =D10-D17 | E19: =E10-E17 | F19: =F10-F17

Sheet 3业务合并损益
B2: 3 业务合并损益表（3 年）
B4: 项 | C4: Y1 | D4: Y2 | E4: Y3 | F4: 3 年累计
B5: 业务 1 钢厂收入 | C5: ='业务1钢厂主业'!C9 | D5: ='业务1钢厂主业'!D9 | E5: ='业务1钢厂主业'!E9 | F5: ='业务1钢厂主业'!F9
B6: 业务 2 钢贸收入 | C6: ='业务2钢贸SaaS'!C10 | D6: ='业务2钢贸SaaS'!D10 | E6: ='业务2钢贸SaaS'!E10 | F6: ='业务2钢贸SaaS'!F10
B7: 业务 3 平台数据收入 | C7: ='业务3平台数据'!C10 | D7: ='业务3平台数据'!D10 | E7: ='业务3平台数据'!E10 | F7: ='业务3平台数据'!F10
B8: 3 业务总收入 | C8: =SUM(C5:C7) | D8: =SUM(D5:D7) | E8: =SUM(E5:E7) | F8: =SUM(F5:F7)
B10: 业务 1 钢厂成本 | C10: ='业务1钢厂主业'!C16 | D10: ='业务1钢厂主业'!D16 | E10: ='业务1钢厂主业'!E16 | F10: ='业务1钢厂主业'!F16
B11: 业务 2 钢贸成本 | C11: ='业务2钢贸SaaS'!C18 | D11: ='业务2钢贸SaaS'!D18 | E11: ='业务2钢贸SaaS'!E18 | F11: ='业务2钢贸SaaS'!F18
B12: 业务 3 平台成本 | C12: ='业务3平台数据'!C17 | D12: ='业务3平台数据'!D17 | E12: ='业务3平台数据'!E17 | F12: ='业务3平台数据'!F17
B13: 3 业务总成本 | C13: =SUM(C10:C12) | D13: =SUM(D10:D12) | E13: =SUM(E10:E12) | F13: =SUM(F10:F12)
B15: 3 业务净利润 | C15: =C8-C13 | D15: =D8-D13 | E15: =E8-E13 | F15: =F8-F13
B17: 净利率 | C17: =C15/C8 | D17: =D15/D8 | E17: =E15/E8

Sheet 协同效应测算
B2: 3 业务协同效应（额外创造价值）
B4: 协同方式 | C4: Y1(¥) | D4: Y2(¥) | E4: Y3(¥) | F4: 说明
B5: 业务 1 客户 → 业务 2 引荐 | C5: 0 | D5: 1500000 | E5: 8000000 | F5: 钢厂的下游钢贸商 → 钢贸 SaaS
B6: 业务 2 客户 → 业务 3 数据 | C6: 0 | D6: 500000 | E6: 5000000 | F6: 钢贸 SaaS 数据沉淀 → 卖银行
B7: 业务 1+2 联合销售 | C7: 200000 | D7: 2000000 | E7: 8000000 | F7: 三位一体方案高客单价
B8: CAC 降低（共享线索） | C8: 100000 | D8: 1500000 | E8: 5000000 | F8: 节省营销 + 销售成本
B9: LTV 提升（交叉销售） | C9: 0 | D9: 2000000 | E9: 12000000 | F9: 客户买多个产品
B10: 数据壁垒带来估值溢价 | F10: 20-50% 估值上浮
B11: 协同总价值（额外） | C11: =SUM(C5:C9) | D11: =SUM(D5:D9) | E11: =SUM(E5:E9)

Sheet 估值与融资
B2: 估值演进 + 融资节奏
B4: 时点 | C4: ARR(¥) | D4: PS 倍数 | E4: 估值(¥) | F4: 建议融资
B5: Y0 末（启动） | C5: 0 | D5: — | E5: 50000000 | F5: 天使 ¥500 万
B6: Y1 末 | C6: 10000000 | D6: 8 | E6: 80000000 | F6: Pre-A ¥3,000 万
B7: Y2 末 | C7: 50000000 | D7: 10 | E7: 500000000 | F7: A 轮 ¥1-3 亿
B8: Y3 末 | C8: 300000000 | D8: 8 | E8: 2400000000 | F8: B 轮 ¥3-10 亿
B9: Y4 末（预测） | C9: 600000000 | D9: 10 | E9: 6000000000 | F9: Pre-IPO ¥10-30 亿
B10: Y5+（预测） | C10: 1200000000 | D10: 12 | E10: 14400000000 | F10: IPO ¥500-1000 亿市值
