Workbook

Sheet 使用说明
B2: 钢铁数字化系统报价单 v2.0（降门槛版）
B4: v2.0 主要变化 | C4: ① 实施费降幅 50-70%，月租降幅 20-30% ② 简化为 3 档套餐价（种子/经营/旗舰），不再按产线累加 ③ 新增 3 种付费模式：A 经典 / B 0首付月供（+30%月租, 36 月）/ C 利润分成 ④ 新增 12 期分期模拟与年支出红线警示
B5: 使用步骤 | C5: ① 打开『报价计算器』，黄色单元格填客户类型、版本、付费模式、客户年利润 ② 绿色单元格自动出报价、月供、年支出占年利润比 ③ 占比超过 1.5%→红色警示，建议调整版本或付费模式 ④ 切换『付费模式对比』看 3 种模式横向对比 ⑤ 切换『3 档版本一览』给客户看完整菜单（不要让客户看全价目表）
B6: 销售铁律 | C6: 1. 永远只给客户看『3 档版本一览』中的 3 个版本，不要打开『价格基准表』 2. 报价话术：先报『月供』，客户问总价再报实施费 3. 实施费默认推 12 期分期，相当于『每月一杯酒钱』 4. 现签现送：30 天月租免单（写进合同）
B7: 权限 | C7: 销售：套餐价 ±5% 自批；销售总监 ±15%；C 模式必须总经理审批；种子版不打折
B8: 注意事项 | C8: 1. 黄色 = 输入区；绿色 = 自动计算；红色 = 警示；蓝色 = 表头 2. 修改『价格基准表』后保存即可，无需改公式 3. C 模式（利润分成）只对灯塔厂候选客户开放，必须 CEO/总经理批

Sheet 价格基准表
A1: 客户类型 | B1: 版本 | C1: 实施费(元) | D1: 月租(元/月) | E1: 含模块 | F1: 适用规模
A2: 开平纵剪加工 | B2: 种子版 | C2: 9800 | D2: 1500 | E2: 成本核算（单产线） | F2: 想先试试的小厂
A3: 开平纵剪加工 | B3: 经营版 | C3: 36000 | D3: 4800 | E3: 成本核算+库存+卷号追溯（≤3 产线） | F3: 80% 主流
A4: 开平纵剪加工 | B4: 旗舰版 | C4: 98000 | D4: 12000 | E4: 全套(ERP+MES+WMS+财务)+不限产线 | F4: 4+ 产线大厂
A5: 钢管生产企业 | B5: 种子版 | C5: 19800 | D5: 3500 | E5: 质量追溯（单产线） | F5: 1-2 产线
A6: 钢管生产企业 | B6: 经营版 | C6: 68000 | D6: 9800 | E6: 追溯+排程+成本（≤5 产线） | F6: 80% 主流
A7: 钢管生产企业 | B7: 旗舰版 | C7: 188000 | D7: 25000 | E7: 全套+EAM+多基地+不限产线 | F7: 6+ 产线大厂
A8: 镀锌冷卷企业 | B8: 种子版 | C8: 36000 | D8: 6800 | E8: 追溯+OEE（单机组） | F8: 单机组试点
A9: 镀锌冷卷企业 | B9: 经营版 | C9: 98000 | D9: 15000 | E9: 追溯+EAM+排程+成本（≤2 机组） | F9: 80% 主流
A10: 镀锌冷卷企业 | B10: 旗舰版 | C10: 250000 | D10: 35000 | E10: 全套+APS接口+多基地 | F10: 3+ 机组大厂
A11: 一体厂 | B11: 种子版 | C11: 68000 | D11: 12000 | E11: 全厂质量追溯（单业务） | F11: 试点先行
A12: 一体厂 | B12: 经营版 | C12: 168000 | D12: 28000 | E12: 全厂追溯+排程+成本 | F12: 80% 主流
A13: 一体厂 | B13: 旗舰版 | C13: 380000 | D13: 58000 | E13: 全套+集团合并报表+BI大屏 | F13: 集团化大厂

Sheet 3档版本一览
B2: 3 档版本菜单（销售给客户看的页面）
B4: ▼ 开平纵剪加工
B5: 项目 | C5: 种子版 | D5: 经营版 | E5: 旗舰版
B6: 实施费(元) | C6: 9800 | D6: 36000 | E6: 98000
B7: 月租起(元/月) | C7: 1500 | D7: 4800 | E7: 12000
B8: 12 期月供合计 | C8: 2320 | D8: 7800 | E8: 20170
B9: 含模块 | C9: 成本核算（单产线） | D9: 成本核算+库存+卷号追溯（≤3 产线） | E9: 全套(ERP+MES+WMS+财务)+不限产线
B10: 适用 | C10: 想先试试的小厂 | D10: 80% 主流 | E10: 4+ 产线大厂
B12: ▼ 钢管生产企业
B13: 项目 | C13: 种子版 | D13: 经营版 | E13: 旗舰版
B14: 实施费(元) | C14: 19800 | D14: 68000 | E14: 188000
B15: 月租起(元/月) | C15: 3500 | D15: 9800 | E15: 25000
B16: 12 期月供合计 | C16: 5150 | D16: 15470 | E16: 40670
B17: 含模块 | C17: 质量追溯（单产线） | D17: 追溯+排程+成本（≤5 产线） | E17: 全套+EAM+多基地+不限产线
B18: 适用 | C18: 1-2 产线 | D18: 80% 主流 | E18: 6+ 产线大厂
B20: ▼ 镀锌冷卷企业
B21: 项目 | C21: 种子版 | D21: 经营版 | E21: 旗舰版
B22: 实施费(元) | C22: 36000 | D22: 98000 | E22: 250000
B23: 月租起(元/月) | C23: 6800 | D23: 15000 | E23: 35000
B24: 12 期月供合计 | C24: 9800 | D24: 23170 | E24: 55830
B25: 含模块 | C25: 追溯+OEE（单机组） | D25: 追溯+EAM+排程+成本（≤2 机组） | E25: 全套+APS接口+多基地
B26: 适用 | C26: 单机组试点 | D26: 80% 主流 | E26: 3+ 机组大厂
B28: ▼ 一体厂
B29: 项目 | C29: 种子版 | D29: 经营版 | E29: 旗舰版
B30: 实施费(元) | C30: 68000 | D30: 168000 | E30: 380000
B31: 月租起(元/月) | C31: 12000 | D31: 28000 | E31: 58000
B32: 12 期月供合计 | C32: 17670 | D32: 42000 | E32: 89670
B33: 含模块 | C33: 全厂质量追溯（单业务） | D33: 全厂追溯+排程+成本 | E33: 全套+集团合并报表+BI大屏
B34: 适用 | C34: 试点先行 | D34: 80% 主流 | E34: 集团化大厂

Sheet 报价计算器
B2: 客户报价计算器（v2.0）
B4: 一、客户基础信息（黄色 = 必填）
B5: 客户全称 | H5: —— 内部计算辅助 ——
B6: 联系人 / 电话 | H6: 基准实施费 | I6: =SUMPRODUCT(('价格基准表'!$A$2:$A$13=$C$7)*('价格基准表'!$B$2:$B$13=$C$8)*'价格基准表'!$C$2:$C$13)
B7: 客户类型 | C7: 钢管生产企业 | H7: 基准月租 | I7: =SUMPRODUCT(('价格基准表'!$A$2:$A$13=$C$7)*('价格基准表'!$B$2:$B$13=$C$8)*'价格基准表'!$D$2:$D$13)
B8: 版本 | C8: 经营版 | H8: 实施费系数 | I8: =IF($C$9="A 经典",1,IF($C$9="B 0首付月供",0,IF($C$9="C 利润分成",0,1)))
B9: 付费模式 | C9: A 经典 | H9: 月租系数 | I9: =IF($C$9="A 经典",1,IF($C$9="B 0首付月供",1.3,IF($C$9="C 利润分成",0.5,1)))
B10: 销售折扣率(0.85~1.00) | C10: 1 | H10: 实付实施费 | I10: =ROUND(I6*I8*$C$10,-2)
B11: 客户年利润(万元) | C11: 1500 | H11: 实付月租 | I11: =ROUND(I7*I9*$C$10,-1)
H12: 12 期月供合计 | I12: =ROUND(I10/12+I11,-1)
B13: 二、自动计算（绿色 = 输出，红色 = 警示）
B15: 一次性实施费 | E15: =I10
B16: 月租（实际） | E16: =I11
B17: 方案 1：一次付实施费 + 月租 | E17: =I10+I11*12
B18: 方案 2：12 期分期月供 | E18: =I12
B19: 3 年总投入 | E19: =I10+I11*36
B20: 销售提成 | E20: =I10*IF($C$8="种子版",0.05,IF($C$8="经营版",0.08,0.10)) + I11*12*IF($C$8="种子版",0.02,IF($C$8="经营版",0.03,0.04))
B22: 首年支出占客户年利润 % | E22: =IFERROR((I10+I11*12)/(C11*10000),0)
B23: 🚨 健康度参考： ≤ 1%：非常健康，可推旗舰版 1-1.5%：合理，建议经营版+12 期分期 1.5-3%：偏高，强烈建议 B 模式（0首付月供）或降版本 > 3%：过高，必须降版本或推种子版试点 🎯 销售三步话术： ① 先报『方案 2 月供』数字 ② 客户问总价再报实施费 ③ 关单送『前 30 天月租免单』

Sheet 付费模式对比
B2: 3 种付费模式横向对比（基于报价计算器输入）
B4: 项目 | C4: A 经典 | D4: B 0首付月供 | E4: C 利润分成
B5: 首付实施费 | C5: ='报价计算器'!I6 | D5: 0 | E5: 0
B6: 月租（元/月） | C6: ='报价计算器'!I7 | D6: ='报价计算器'!I7*1.3 | E6: ='报价计算器'!I7*0.5
B7: 12 个月支出 | C7: ='报价计算器'!I6+'报价计算器'!I7*12 | D7: ='报价计算器'!I7*1.3*12 | E7: ='报价计算器'!I7*0.5*12 + 0
B8: 36 个月支出 | C8: ='报价计算器'!I6+'报价计算器'!I7*36 | D8: ='报价计算器'!I7*1.3*36 | E8: ='报价计算器'!I7*0.5*36 + 0
B9: 适合客户类型 | C9: 现金流好、不喜分期 | D9: 现金紧、抠门老板 | E9: 高利润大客户、灯塔候选
B10: 销售难度 | C10: ★★★ | D10: ★★ | E10: ★（最易成交）
B11: 公司利润 | C11: 稳健 | D11: 前低后高 | E11: 极高（封顶 1.5x）

Sheet 12期分期模拟
B2: 12 期分期月供模拟（基于报价计算器输入）
B4: 期数 | C4: 实施费分期 | D4: 月租 | E4: 当月合计
B5: 第 1 月 | C5: ='报价计算器'!I10/12 | D5: ='报价计算器'!I11 | E5: =C5+D5
B6: 第 2 月 | C6: ='报价计算器'!I10/12 | D6: ='报价计算器'!I11 | E6: =C6+D6
B7: 第 3 月 | C7: ='报价计算器'!I10/12 | D7: ='报价计算器'!I11 | E7: =C7+D7
B8: 第 4 月 | C8: ='报价计算器'!I10/12 | D8: ='报价计算器'!I11 | E8: =C8+D8
B9: 第 5 月 | C9: ='报价计算器'!I10/12 | D9: ='报价计算器'!I11 | E9: =C9+D9
B10: 第 6 月 | C10: ='报价计算器'!I10/12 | D10: ='报价计算器'!I11 | E10: =C10+D10
B11: 第 7 月 | C11: ='报价计算器'!I10/12 | D11: ='报价计算器'!I11 | E11: =C11+D11
B12: 第 8 月 | C12: ='报价计算器'!I10/12 | D12: ='报价计算器'!I11 | E12: =C12+D12
B13: 第 9 月 | C13: ='报价计算器'!I10/12 | D13: ='报价计算器'!I11 | E13: =C13+D13
B14: 第 10 月 | C14: ='报价计算器'!I10/12 | D14: ='报价计算器'!I11 | E14: =C14+D14
B15: 第 11 月 | C15: ='报价计算器'!I10/12 | D15: ='报价计算器'!I11 | E15: =C15+D15
B16: 第 12 月 | C16: ='报价计算器'!I10/12 | D16: ='报价计算器'!I11 | E16: =C16+D16
B17: 12 期合计 | C17: =SUM(C5:C16) | D17: =SUM(D5:D16) | E17: =SUM(E5:E16)
B19: 💬 现场销售话术： "X 总，您看这一栏（指 E 列）：每月总共付 ¥XX，相当于多请一个不要五险一金的数字化助理，3 年下来比您一台二手叉车还便宜。 12 期分期免息，是我们和 XX 银行特别谈的合作政策， 现在签还送『前 30 天月租免单』，您可以先试一个月再决定要不要继续。"

Sheet 返佣测算
B2: 推荐返佣测算（基于报价计算器输入）
B4: 推荐人类型 | C4: 实施费返佣 | D4: 月租返佣 | E4: 返佣月数 | F4: 返佣金额合计 | G4: 结算说明
B5: 老客户（现金） | C5: 0.1 | D5: 0.05 | E5: 12 | F5: ='报价计算器'!I10*C5 + '报价计算器'!I11*D5*E5 | G5: 现金或对公
B6: 老客户（抵自家月租 双倍） | C6: 0.2 | D6: 0.1 | E6: 12 | F6: ='报价计算器'!I10*C6 + '报价计算器'!I11*D6*E6 | G6: 抵扣本人月订阅费
B7: 行业顾问 / KOL | C7: 0.15 | D7: 0.08 | E7: 24 | F7: ='报价计算器'!I10*C7 + '报价计算器'!I11*D7*E7 | G7: 对公月结
B8: 区域代理（独家） | C8: 0.38 | D8: 0.2 | E8: 36 | F8: ='报价计算器'!I10*C8 + '报价计算器'!I11*D8*E8 | G8: 月结，需达业绩门槛
B9: 设备厂商联合 | C9: 0.2 | D9: 0.1 | E9: 18 | F9: ='报价计算器'!I10*C9 + '报价计算器'!I11*D9*E9 | G9: 季结
